setup.py
Gaus_Bio_distributions/Binomialdistribution.py
Gaus_Bio_distributions/Gaussiandistribution.py
Gaus_Bio_distributions/Generaldistribution.py
Gaus_Bio_distributions/__init__.py
Gaus_Bio_distributions.egg-info/PKG-INFO
Gaus_Bio_distributions.egg-info/SOURCES.txt
Gaus_Bio_distributions.egg-info/dependency_links.txt
Gaus_Bio_distributions.egg-info/not-zip-safe
Gaus_Bio_distributions.egg-info/top_level.txt