Metadata-Version: 1.0
Name: Gaus-Bio-distributions
Version: 1.0
Summary: Gaussian and Binomial distributions
Home-page: UNKNOWN
Author: Francis Obasi
Author-email: obasichigoziefrancis@gmail.com
License: UNKNOWN
Platform: UNKNOWN
